duckdb_extension_arrow/__init__.py
duckdb_extension_arrow/extensions/v1.2.1/arrow.duckdb_extension
duckdb_extension_arrow-1.2.1.dist-info/METADATA
duckdb_extension_arrow-1.2.1.dist-info/WHEEL
duckdb_extension_arrow-1.2.1.dist-info/RECORD
